podpuller/__init__.py
podpuller/__main__.py
podpuller/db.py
podpuller/podpuller.py
podpuller/process.py
podpuller/ui.py
podpuller-1.4.6.dist-info/LICENSE
podpuller-1.4.6.dist-info/METADATA
podpuller-1.4.6.dist-info/WHEEL
podpuller-1.4.6.dist-info/entry_points.txt
podpuller-1.4.6.dist-info/top_level.txt
podpuller-1.4.6.dist-info/RECORD
