Metadata-Version: 2.1
Name: podpuller
Version: 1.4.6
Summary: A simple command line podcast feed syncer
Home-page: https://github.com/guyhoffman/podpuller
Author: Guy Hoffman
Author-email: code@guyhoffman.com
License: MIT
Keywords: podcasts rss feeds cli
Requires-Python: >=3.7
License-File: LICENSE
Requires-Dist: requests
Requires-Dist: SQLObject
Requires-Dist: tqdm
Requires-Dist: bullet
Requires-Dist: termcolor
Requires-Dist: feedparser
Requires-Dist: eyed3
